file_converter/__init__.py
file_converter/docx.py
file_converter/jpg.py
file_converter/pdf.py
file_converter/png.py
file_converter/exceptions/__init__.py
file_converter/types/__init__.py
file_converter/types/document.py
file_converter/types/image.py
file_converter/utils/__init__.py
file_converter/utils/tmp_file_manager.py
multi_file_converter-1.0.9.dist-info/METADATA
multi_file_converter-1.0.9.dist-info/WHEEL
multi_file_converter-1.0.9.dist-info/top_level.txt
multi_file_converter-1.0.9.dist-info/RECORD
