Metadata-Version: 2.1
Name: multi-file-converter
Version: 1.0.9
Summary: Simple way to convert files to another formats
Home-page: https://github.com/DAKExDUCK/FileConverter
Author: dake_duck
Author-email: arsengabdulin228@gmail.com
Project-URL: GitHub, https://github.com/DAKExDUCK/FileConverter
Classifier: Programming Language :: Python :: 3.10
Classifier: Operating System :: POSIX :: Linux
Requires-Python: >=3.10
Requires-Dist: Pillow (>=10.0.0)
